typedb_jupyter/__init__.py
typedb_jupyter/connection.py
typedb_jupyter/exception.py
typedb_jupyter/magic.py
typedb_jupyter/query.py
typedb_jupyter-0.3.dist-info/LICENSE
typedb_jupyter-0.3.dist-info/METADATA
typedb_jupyter-0.3.dist-info/WHEEL
typedb_jupyter-0.3.dist-info/top_level.txt
typedb_jupyter-0.3.dist-info/RECORD
