Metadata-Version: 2.1
Name: typedb-jupyter
Version: 0.3
Summary: Jupyter connector for TypeDB
Author-email: James Whiteside <james.whiteside@vaticle.com>
License: Apache License
Project-URL: Repository, https://github.com/typedb-osi/typedb-jupyter
Project-URL: Release notes, https://github.com/typedb-osi/typedb-jupyter/blob/master/RELEASE_NOTES.md
Project-URL: TypeDB, https://github.com/vaticle/typedb
Project-URL: Vaticle, https://vaticle.com/
Classifier: Development Status :: 4 - Beta
Classifier: Environment :: Console
Classifier: Framework :: IPython
Classifier: License :: OSI Approved :: Apache Software License
Classifier: Natural Language :: English
Classifier: Programming Language :: Python :: 3
Classifier: Topic :: Database
Requires-Python: >=3.7
License-File: LICENSE
Requires-Dist: typedb-client (~=2.17)
Requires-Dist: ipython
